README.rst
geniatagger.py
setup.py
geniatagger_python.egg-info/PKG-INFO
geniatagger_python.egg-info/SOURCES.txt
geniatagger_python.egg-info/dependency_links.txt
geniatagger_python.egg-info/top_level.txt