Metadata-Version: 1.0
Name: geniatagger-python
Version: 0.1
Summary: Python library for GeniaTagger
Home-page: https://github.com/informationsea/geniatagger-python
Author: OKAMURA Yasunobu
Author-email: UNKNOWN
License: UNKNOWN
Platform: UNKNOWN
